README.md
setup.cfg
setup.py
lognormal_stats/__init__.py
lognormal_stats.egg-info/PKG-INFO
lognormal_stats.egg-info/SOURCES.txt
lognormal_stats.egg-info/dependency_links.txt
lognormal_stats.egg-info/not-zip-safe
lognormal_stats.egg-info/requires.txt
lognormal_stats.egg-info/top_level.txt